MANIFEST.in
README.md
setup.py
bin/brail
brail/__init__.py
brail/brail.py
brail/conf.py
brail/diff.py
brail/editor.py
brail/errors.py
brail/git.py
brail/output.py
brail/postgrator.py
brail/records.py
brail/test_diff.py
brail/test_postgrator.py
brail/usage.py
brail.egg-info/PKG-INFO
brail.egg-info/SOURCES.txt
brail.egg-info/dependency_links.txt
brail.egg-info/not-zip-safe
brail.egg-info/top_level.txt