Metadata-Version: 1.2
Name: brail
Version: 0.6
Summary: Command-line tool for managing releases
Home-page: http://github.com/Portchain/brail
Author: Sergei Patiakin
Author-email: sergei.patiakin@gmail.com
License: Proprietary
Platform: UNKNOWN
Requires-Python: >=3.5
